[{"mode":"train","service":"22100001","train_uid":"Y81255","platform":"6","operator":"VT","aimed_departure_time":null,"expected_departure_time":null,"best_departure_estimate_mins":null,"aimed_arrival_time":"2014-04-06T13:18:00.000Z","expected_arrival_time":"2014-04-06T13:54:00.000Z","best_arrival_estimate_mins":1,"status":"LATE","source":"Network Rail","origin_code":"BHM","destination_code":"EUS"},{"mode":"train","service":"22112001","train_uid":"Y81654","platform":"13","operator":"VT","aimed_departure_time":null,"expected_departure_time":null,"best_departure_estimate_mins":null,"aimed_arrival_time":"2014-04-06T13:25:00.000Z","expected_arrival_time":"2014-04-06T13:59:00.000Z","best_arrival_estimate_mins":6,"status":"LATE","source":"Network Rail","origin_code":"GLC","destination_code":"EUS"},{"mode":"train","service":"22100001","train_uid":"Y81257","platform":"4","operator":"VT","aimed_departure_time":null,"expected_departure_time":null,"best_departure_estimate_mins":null,"aimed_arrival_time":"2014-04-06T13:38:00.000Z","expected_arrival_time":"2014-04-06T14:01:00.000Z","best_arrival_estimate_mins":8,"status":"LATE","source":"Network Rail","origin_code":"WVH","destination_code":"EUS"},{"mode":"train","service":"22104001","train_uid":"Y81075","platform":"4","operator":"VT","aimed_departure_time":null,"expected_departure_time":null,"best_departure_estimate_mins":null,"aimed_arrival_time":"2014-04-06T13:44:00.000Z","expected_arrival_time":"2014-04-06T13:52:00.000Z","best_arrival_estimate_mins":-1,"status":"LATE","source":"Network Rail","origin_code":"CTR","destination_code":"EUS"},{"mode":"train","service":"22330000","train_uid":"G23286","platform":"10","operator":"LM","aimed_departure_time":null,"expected_departure_time":null,"best_departure_estimate_mins":null,"aimed_arrival_time":"2014-04-06T13:53:00.000Z","expected_arrival_time":"2014-04-06T13:58:00.000Z","best_arrival_estimate_mins":5,"status":"LATE","source":"Network Rail","origin_code":"CRE","destination_code":"EUS"},{"mode":"train","service":"22100001","train_uid":"Y81261","platform":"1","operator":"VT","aimed_departure_time":null,"expected_departure_time":null,"best_departure_estimate_mins":null,"aimed_arrival_time":"2014-04-06T13:57:00.000Z","expected_arrival_time":"2014-04-06T14:17:00.000Z","best_arrival_estimate_mins":24,"status":"LATE","source":"Network Rail","origin_code":"BHM","destination_code":"EUS"},{"mode":"train","service":"22109001","train_uid":"Y81083","platform":"6","operator":"VT","aimed_departure_time":null,"expected_departure_time":null,"best_departure_estimate_mins":null,"aimed_arrival_time":"2014-04-06T14:04:00.000Z","expected_arrival_time":"2014-04-06T14:05:00.000Z","best_arrival_estimate_mins":12,"status":"LATE","source":"Network Rail","origin_code":"LIV","destination_code":"EUS"},{"mode":"train","service":"22108001","train_uid":"Y81086","platform":"2","operator":"VT","aimed_departure_time":null,"expected_departure_time":null,"best_departure_estimate_mins":null,"aimed_arrival_time":"2014-04-06T14:08:00.000Z","expected_arrival_time":"2014-04-06T14:08:00.000Z","best_arrival_estimate_mins":15,"status":"EARLY","source":"Network Rail","origin_code":"MAN","destination_code":"EUS"},{"mode":"train","service":"22216000","train_uid":"L36068","platform":"9","operator":"LO","aimed_departure_time":null,"expected_departure_time":null,"best_departure_estimate_mins":null,"aimed_arrival_time":"2014-04-06T14:10:00.000Z","expected_arrival_time":"2014-04-06T14:11:00.000Z","best_arrival_estimate_mins":18,"status":"LATE","source":"Network Rail","origin_code":"WFJ","destination_code":"EUS"},{"mode":"train","service":"22112001","train_uid":"Y81661","platform":"13","operator":"VT","aimed_departure_time":null,"expected_departure_time":null,"best_departure_estimate_mins":null,"aimed_arrival_time":"2014-04-06T14:13:00.000Z","expected_arrival_time":"2014-04-06T14:30:00.000Z","best_arrival_estimate_mins":37,"status":"LATE","source":"Network Rail","origin_code":"GLC","destination_code":"EUS"},{"mode":"train","service":"22209000","train_uid":"G24037","platform":"8","operator":"LM","aimed_departure_time":null,"expected_departure_time":null,"best_departure_estimate_mins":null,"aimed_arrival_time":"2014-04-06T14:17:00.000Z","expected_arrival_time":"2014-04-06T14:22:00.000Z","best_arrival_estimate_mins":29,"status":"LATE","source":"Network Rail","origin_code":"MKC","destination_code":"EUS"},{"mode":"train","service":"22100001","train_uid":"Y81266","platform":"7","operator":"VT","aimed_departure_time":null,"expected_departure_time":null,"best_departure_estimate_mins":null,"aimed_arrival_time":"2014-04-06T14:18:00.000Z","expected_arrival_time":"2014-04-06T14:27:00.000Z","best_arrival_estimate_mins":34,"status":"LATE","source":"Network Rail","origin_code":"BHM","destination_code":"EUS"},{"mode":"train","service":"22108001","train_uid":"Y81091","platform":"14","operator":"VT","aimed_departure_time":null,"expected_departure_time":null,"best_departure_estimate_mins":null,"aimed_arrival_time":"2014-04-06T14:26:00.000Z","expected_arrival_time":"2014-04-06T14:28:00.000Z","best_arrival_estimate_mins":35,"status":"LATE","source":"Network Rail","origin_code":"MAN","destination_code":"EUS"},{"mode":"train","service":"22216000","train_uid":"L36071","platform":"9","operator":"LO","aimed_departure_time":null,"expected_departure_time":null,"best_departure_estimate_mins":null,"aimed_arrival_time":"2014-04-06T14:31:00.000Z","expected_arrival_time":"2014-04-06T14:31:00.000Z","best_arrival_estimate_mins":38,"status":"ON TIME","source":"Network Rail","origin_code":"WFJ","destination_code":"EUS"},{"mode":"train","service":"12259320","train_uid":"G25478","platform":"11","operator":"LM","aimed_departure_time":null,"expected_departure_time":null,"best_departure_estimate_mins":null,"aimed_arrival_time":"2014-04-06T14:37:00.000Z","expected_arrival_time":"2014-04-06T14:38:00.000Z","best_arrival_estimate_mins":45,"status":"LATE","source":"Network Rail","origin_code":"BHM","destination_code":"EUS"},{"mode":"train","service":"22114001","train_uid":"Y81501","platform":"5","operator":"VT","aimed_departure_time":null,"expected_departure_time":null,"best_departure_estimate_mins":null,"aimed_arrival_time":"2014-04-06T14:39:00.000Z","expected_arrival_time":"2014-04-06T14:49:00.000Z","best_arrival_estimate_mins":56,"status":"LATE","source":"Network Rail","origin_code":"LAN","destination_code":"EUS"},{"mode":"train","service":"22104001","train_uid":"Y81096","platform":"4","operator":"VT","aimed_departure_time":null,"expected_departure_time":null,"best_departure_estimate_mins":null,"aimed_arrival_time":"2014-04-06T14:45:00.000Z","expected_arrival_time":"2014-04-06T14:45:00.000Z","best_arrival_estimate_mins":52,"status":"NO REPORT","source":"Network Rail","origin_code":"CTR","destination_code":"EUS"},{"mode":"train","service":"22108001","train_uid":"Y81099","platform":"4","operator":"VT","aimed_departure_time":null,"expected_departure_time":null,"best_departure_estimate_mins":null,"aimed_arrival_time":"2014-04-06T14:48:00.000Z","expected_arrival_time":"2014-04-06T14:52:00.000Z","best_arrival_estimate_mins":59,"status":"LATE","source":"Network Rail","origin_code":"MAN","destination_code":"EUS"},{"mode":"train","service":"22216000","train_uid":"L36074","platform":"9","operator":"LO","aimed_departure_time":null,"expected_departure_time":null,"best_departure_estimate_mins":null,"aimed_arrival_time":"2014-04-06T14:50:00.000Z","expected_arrival_time":"2014-04-06T14:50:00.000Z","best_arrival_estimate_mins":57,"status":"ON TIME","source":"Network Rail","origin_code":"WFJ","destination_code":"EUS"},{"mode":"train","service":"22330000","train_uid":"G23288","platform":"10","operator":"LM","aimed_departure_time":null,"expected_departure_time":null,"best_departure_estimate_mins":null,"aimed_arrival_time":"2014-04-06T14:53:00.000Z","expected_arrival_time":"2014-04-06T14:54:00.000Z","best_arrival_estimate_mins":61,"status":"LATE","source":"Network Rail","origin_code":"CRE","destination_code":"EUS"},{"mode":"train","service":"22100001","train_uid":"Y81274","platform":"3","operator":"VT","aimed_departure_time":null,"expected_departure_time":null,"best_departure_estimate_mins":null,"aimed_arrival_time":"2014-04-06T14:57:00.000Z","expected_arrival_time":"2014-04-06T14:58:00.000Z","best_arrival_estimate_mins":65,"status":"LATE","source":"Network Rail","origin_code":"BHM","destination_code":"EUS"},{"mode":"train","service":"22109001","train_uid":"Y81104","platform":"1","operator":"VT","aimed_departure_time":null,"expected_departure_time":null,"best_departure_estimate_mins":null,"aimed_arrival_time":"2014-04-06T15:04:00.000Z","expected_arrival_time":"2014-04-06T15:04:00.000Z","best_arrival_estimate_mins":71,"status":"ON TIME","source":"Network Rail","origin_code":"LIV","destination_code":"EUS"},{"mode":"train","service":"22108001","train_uid":"Y81107","platform":"2","operator":"VT","aimed_departure_time":null,"expected_departure_time":null,"best_departure_estimate_mins":null,"aimed_arrival_time":"2014-04-06T15:07:00.000Z","expected_arrival_time":"2014-04-06T15:07:00.000Z","best_arrival_estimate_mins":74,"status":"ON TIME","source":"Network Rail","origin_code":"MAN","destination_code":"EUS"},{"mode":"train","service":"22216000","train_uid":"L36077","platform":"9","operator":"LO","aimed_departure_time":null,"expected_departure_time":null,"best_departure_estimate_mins":null,"aimed_arrival_time":"2014-04-06T15:10:00.000Z","expected_arrival_time":"2014-04-06T15:10:00.000Z","best_arrival_estimate_mins":77,"status":"ON TIME","source":"Network Rail","origin_code":"WFJ","destination_code":"EUS"},{"mode":"train","service":"22112001","train_uid":"Y81676","platform":"13","operator":"VT","aimed_departure_time":null,"expected_departure_time":null,"best_departure_estimate_mins":null,"aimed_arrival_time":"2014-04-06T15:13:00.000Z","expected_arrival_time":"2014-04-06T15:14:00.000Z","best_arrival_estimate_mins":81,"status":"LATE","source":"Network Rail","origin_code":"GLC","destination_code":"EUS"},{"mode":"train","service":"22209000","train_uid":"G24053","platform":"8","operator":"LM","aimed_departure_time":null,"expected_departure_time":null,"best_departure_estimate_mins":null,"aimed_arrival_time":"2014-04-06T15:17:00.000Z","expected_arrival_time":"2014-04-06T15:17:00.000Z","best_arrival_estimate_mins":84,"status":"ON TIME","source":"Network Rail","origin_code":"MKC","destination_code":"EUS"},{"mode":"train","service":"22100001","train_uid":"Y81278","platform":"6","operator":"VT","aimed_departure_time":null,"expected_departure_time":null,"best_departure_estimate_mins":null,"aimed_arrival_time":"2014-04-06T15:18:00.000Z","expected_arrival_time":"2014-04-06T15:18:00.000Z","best_arrival_estimate_mins":85,"status":"LATE","source":"Network Rail","origin_code":"BHM","destination_code":"EUS"},{"mode":"train","service":"22108001","train_uid":"Y81112","platform":"16","operator":"VT","aimed_departure_time":null,"expected_departure_time":null,"best_departure_estimate_mins":null,"aimed_arrival_time":"2014-04-06T15:26:00.000Z","expected_arrival_time":"2014-04-06T15:26:00.000Z","best_arrival_estimate_mins":93,"status":"EARLY","source":"Network Rail","origin_code":"MAN","destination_code":"EUS"},{"mode":"train","service":"22216000","train_uid":"L36080","platform":"9","operator":"LO","aimed_departure_time":null,"expected_departure_time":null,"best_departure_estimate_mins":null,"aimed_arrival_time":"2014-04-06T15:31:00.000Z","expected_arrival_time":"2014-04-06T15:31:00.000Z","best_arrival_estimate_mins":98,"status":"ON TIME","source":"Network Rail","origin_code":"WFJ","destination_code":"EUS"},{"mode":"train","service":"12259320","train_uid":"G25487","platform":"11","operator":"LM","aimed_departure_time":null,"expected_departure_time":null,"best_departure_estimate_mins":null,"aimed_arrival_time":"2014-04-06T15:38:00.000Z","expected_arrival_time":"2014-04-06T15:48:00.000Z","best_arrival_estimate_mins":115,"status":"LATE","source":"Network Rail","origin_code":"BHM","destination_code":"EUS"},{"mode":"train","service":"22114001","train_uid":"Y81737","platform":"7","operator":"VT","aimed_departure_time":null,"expected_departure_time":null,"best_departure_estimate_mins":null,"aimed_arrival_time":"2014-04-06T15:39:00.000Z","expected_arrival_time":"2014-04-06T15:43:00.000Z","best_arrival_estimate_mins":110,"status":"LATE","source":"Network Rail","origin_code":"EDP","destination_code":"EUS"},{"mode":"train","service":"22104001","train_uid":"Y81117","platform":"4","operator":"VT","aimed_departure_time":null,"expected_departure_time":null,"best_departure_estimate_mins":null,"aimed_arrival_time":"2014-04-06T15:44:00.000Z","expected_arrival_time":"2014-04-06T15:44:00.000Z","best_arrival_estimate_mins":111,"status":"ON TIME","source":"Network Rail","origin_code":"CTR","destination_code":"EUS"},{"mode":"train","service":"22108001","train_uid":"Y81120","platform":"4","operator":"VT","aimed_departure_time":null,"expected_departure_time":null,"best_departure_estimate_mins":null,"aimed_arrival_time":"2014-04-06T15:48:00.000Z","expected_arrival_time":"2014-04-06T15:48:00.000Z","best_arrival_estimate_mins":115,"status":"ON TIME","source":"Network Rail","origin_code":"MAN","destination_code":"EUS"},{"mode":"train","service":"22216000","train_uid":"L36083","platform":"9","operator":"LO","aimed_departure_time":null,"expected_departure_time":null,"best_departure_estimate_mins":null,"aimed_arrival_time":"2014-04-06T15:50:00.000Z","expected_arrival_time":"2014-04-06T15:50:00.000Z","best_arrival_estimate_mins":117,"status":"ON TIME","source":"Network Rail","origin_code":"WFJ","destination_code":"EUS"}]